{
  "orderId": "1771121087060",
  "name": "Syasa",
  "phone": "6281235303421",
  "notes": "",
  "orderFor": "2026-02-15T02:04:45.457Z",
  "totalPrice": 25000,
  "items": [
    {
      "title": "Dimsum Mentai Large",
      "price": 25000,
      "total": 27000,
      "variants": [
        {
          "name": "Mentai",
          "qty": 6,
          "price": 4500
        }
      ],
      "addons": [
        {
          "name": "Saus Chili Oil",
          "qty": 1,
          "price": 2000
        }
      ],
      "discount": 2000,
      "notes": ""
    }
  ],
  "createdAt": "2026-02-15T02:04:47.777Z",
  "status": "waiting"
}